MANIFEST.in
README.md
setup.cfg
setup.py
geoshape/__init__.py
geoshape/celery_app.py
geoshape/local_settings.py
geoshape/settings.py
geoshape/urls.py
geoshape/version.py
geoshape/views.py
geoshape/wsgi.py
geoshape.egg-info/PKG-INFO
geoshape.egg-info/SOURCES.txt
geoshape.egg-info/dependency_links.txt
geoshape.egg-info/not-zip-safe
geoshape.egg-info/requires.txt
geoshape.egg-info/top_level.txt
geoshape/core/__init__.py
geoshape/core/context_processors.py
geoshape/core/models.py
geoshape/core/management/__init__.py
geoshape/core/management/commands/__init__.py
geoshape/core/management/commands/geogit-sync.py
geoshape/core/management/commands/siteupdate.py
geoshape/core/management/commands/update-layer-ips.py
geoshape/core/tests/__init__.py
geoshape/fileservice/__init__.py
geoshape/fileservice/api.py
geoshape/fileservice/helpers.py