Metadata-Version: 1.1
Name: geoshape
Version: 1.7.1
Summary: geoshape, based on GeoNode and contains additional changes and services
Home-page: https://github.com/ROGUE-JCTD/rogue_geonode
Author: Prominent Edge
Author-email: geoshape.org@gmail.com
License: BSD
Keywords: geoshape geonode django
Platform: UNKNOWN
Classifier: Development Status :: 5 - Production/Stable
